{"frames": [{"frame": {"y": 558, "x": 155, "w": 152, "h": 44}, "spriteSourceSize": {"y": 0, "x": 0, "w": 152, "h": 44}, "sourceSize": {"h": 44, "w": 152}, "filename": "popup/button.png"}, {"frame": {"y": 512, "x": 1, "w": 280, "h": 44}, "spriteSourceSize": {"y": 0, "x": 0, "w": 280, "h": 44}, "sourceSize": {"h": 44, "w": 280}, "filename": "popup/button2_pressed.png"}, {"frame": {"y": 1, "x": 1, "w": 649, "h": 417}, "spriteSourceSize": {"y": 0, "x": 0, "w": 649, "h": 417}, "sourceSize": {"h": 417, "w": 649}, "filename": "popup/background.png"}, {"frame": {"y": 420, "x": 1, "w": 621, "h": 44}, "spriteSourceSize": {"y": 0, "x": 0, "w": 621, "h": 44}, "sourceSize": {"h": 44, "w": 621}, "filename": "popup/button3_pressed.png"}, {"frame": {"y": 512, "x": 283, "w": 280, "h": 44}, "spriteSourceSize": {"y": 0, "x": 0, "w": 280, "h": 44}, "sourceSize": {"h": 44, "w": 280}, "filename": "popup/button2.png"}, {"frame": {"y": 466, "x": 1, "w": 621, "h": 44}, "spriteSourceSize": {"y": 0, "x": 0, "w": 621, "h": 44}, "sourceSize": {"h": 44, "w": 621}, "filename": "popup/button3.png"}, {"frame": {"y": 558, "x": 1, "w": 152, "h": 44}, "spriteSourceSize": {"y": 0, "x": 0, "w": 152, "h": 44}, "sourceSize": {"h": 44, "w": 152}, "filename": "popup/button_pressed.png"}], "meta": {"hash": "8e2d4e3032", "name": "global_popup", "height": 603, "sprite_path": "global_popup.png", "width": 651, "version": "0.10.0", "sprite_filename": "global_popup.png"}}